pyarchops_os_updates/__init__.py
pyarchops_os_updates/os_updates.py
pyarchops_os_updates-0.0.4.dist-info/AUTHORS.rst
pyarchops_os_updates-0.0.4.dist-info/LICENSE
pyarchops_os_updates-0.0.4.dist-info/METADATA
pyarchops_os_updates-0.0.4.dist-info/WHEEL
pyarchops_os_updates-0.0.4.dist-info/top_level.txt
pyarchops_os_updates-0.0.4.dist-info/RECORD
