Metadata-Version: 2.1
Name: pyarchops-os-updates
Version: 0.0.4
Summary: Install All OS updates
Home-page: https://github.com/pyarchops/os_updates
Author: Azul
Author-email: pyarchops@azulinho.com
License: MIT license
Keywords: pyarchops_os_updates
Platform: UNKNOWN
Classifier: Development Status :: 2 - Pre-Alpha
Classifier: Intended Audience :: Developers
Classifier: License :: OSI Approved :: MIT License
Classifier: Natural Language :: English
Classifier: Programming Language :: Python :: 3.7
Requires-Dist: suitable
